izzy/__init__.py
izzy/_version.py
izzy/defaults.py
izzy/classification/__init__.py
izzy/classification/_utilities.py
izzy/classification/generic.py
izzy/classification/logistic.py
izzy/classification/metrics.py
izzy/classification/test.py
izzy/classification/test_black.py
izzy/classification/tree.py
izzy/core/__init__.py
izzy/core/framework.py
izzy/datasets/__init__.py
izzy/datasets/datasets.py
izzy/eda/__init__.py
izzy/eda/analyzer.py
izzy/eda/report.py
izzy/features/Feature.py
izzy/features/__init__.py
izzy/features/clean.py
izzy/features/eda.py
izzy/features/impute.py
izzy/features/transform.py
izzy/financial/financial.py
izzy/math/__init__.py
izzy/math/algebra.py
izzy/math/calculus.py
izzy/math/constants.py
izzy/math/functions.py
izzy/math/geometry.py
izzy/math/operations.py
izzy/misc/__init__.py
izzy/misc/assertions.py
izzy/misc/functions.py
izzy/misc/pipe.py
izzy/misc/types.py
izzy/misc/xpandas.py
izzy/regression/__init__.py
izzy/regression/regression.py
izzy/statistics/__init__.py
izzy/statistics/statistics_functions.py
izzy/tests/__init__.py
izzy/tests/test.py
izzy/tests/test_numpy.py
izzy/tests/test_pandas.py
izzy/tests/test_scipy.py
izzy/tests/test_sklearn.py
izzy/tests/classification/__init__.py
izzy/tests/classification/test_generic.py
izzy/tests/classification/test_metrics.py
izzy/viz/__init__.py
izzy/viz/viz.py
izzy/viz/viz0.py
izzy-0.3.85.dist-info/LICENSE.md
izzy-0.3.85.dist-info/METADATA
izzy-0.3.85.dist-info/WHEEL
izzy-0.3.85.dist-info/top_level.txt
izzy-0.3.85.dist-info/zip-safe
izzy-0.3.85.dist-info/RECORD
