Metadata-Version: 2.1
Name: izzy
Version: 0.3.85
Summary: A toolkit for executing and analyzing machine learning classification
Home-page: https://www.lockhartlab.org
Author: C. Lockhart
Author-email: chris@lockhartlab.org
License: UNKNOWN
Platform: UNKNOWN
Requires-Dist: codecov
Requires-Dist: coverage
Requires-Dist: gitpipe
Requires-Dist: hypothesis
Requires-Dist: iox
Requires-Dist: IPython
Requires-Dist: matplotlib
Requires-Dist: numpy
Requires-Dist: numpy-financial
Requires-Dist: openpyxl
Requires-Dist: pandas
Requires-Dist: plotnine
Requires-Dist: privatize
Requires-Dist: pyyaml
Requires-Dist: scikit-learn
Requires-Dist: scipy
Requires-Dist: sphinx
Requires-Dist: six
Requires-Dist: typelike (>=0.0.31)
